{
  "dct_description_sm": [
    "This polygon dataset is a 100 foot grid overlay for Cambridge, MA."
  ],
  "dct_format_s": "Shapefile",
  "dct_identifier_sm": ["urn:geodata.tufts.edu:Tufts.CambridgeGrid100_04"],
  "dct_language_sm": ["eng"],
  "dct_publisher_sm": ["Cambridge (Mass.) Geographic Information Systems"],
  "dct_accessRights_s": "Public",
  "dct_title_s": "100 Foot Grid Cambridge MA 2004",
  "dct_references_s": "{\"http://www.opengis.net/def/serviceType/ogc/wfs\":\"http://geoserver01.uit.tufts.edu/wfs\",\"http://www.opengis.net/def/serviceType/ogc/wms\":\"http://geoserver01.uit.tufts.edu/wms\",\"http://www.opengis.net/cat/csw/csdgm\":\"http://opengeometadata.stanford.edu/metadata/org.opengeoportal/sde:GISPORTAL.GISOWNER01.CAMBRIDGEGRID100_04/fgdc.xml\",\"http://www.w3.org/1999/xhtml\":\"http://opengeometadata.stanford.edu/metadata/org.opengeoportal/sde:GISPORTAL.GISOWNER01.CAMBRIDGEGRID100_04/fgdc.html\"}",
  "dct_temporal_sm": ["2004"],
  "dct_issued_s": "2005",
  "schema_provider_s": "Tufts",
  "georss_box_s": "42.34757 -71.163984 42.408316 -71.052581",
  "georss_polygon_s": "42.408316 -71.163984 42.408316 -71.052581 42.34757 -71.052581 42.34757 -71.163984 42.408316 -71.163984",
  "id": "tufts-cambridgegrid100-04",
  "gbl_wxsIdentifier_s": "sde:GISPORTAL.GISOWNER01.CAMBRIDGEGRID100_04",
  "gbl_mdModified_dt": "2014-12-04T21:33:07Z",
  "dcat_bbox": "ENVELOPE(-71.163984, -71.052581, 42.408316, 42.34757)",
	"locn_geometry": "ENVELOPE(-71.163984, -71.052581, 42.408316, 42.34757)",
  "gbl_indexYear_im": [2004],
  "gbl_resourceClass_sm": ["Datasets"],
  "gbl_resourceType_sm": ["Polygon data"],
  "gbl_mdVersion_s": "Aardvark"
}
